{
  "hash": "cf93887d",
  "configHash": "bb5ce34f",
  "lockfileHash": "a1427a88",
  "browserHash": "48a7e07c",
  "optimized": {
    "vue": {
      "src": "../../../../node_modules/vue/dist/vue.runtime.esm-bundler.js",
      "file": "vue.js",
      "fileHash": "28baaf51",
      "needsInterop": false
    },
    "vitepress > @vue/devtools-api": {
      "src": "../../../../node_modules/@vue/devtools-api/dist/index.js",
      "file": "vitepress___@vue_devtools-api.js",
      "fileHash": "76b69dc7",
      "needsInterop": false
    },
    "vitepress > @vueuse/core": {
      "src": "../../../../node_modules/@vueuse/core/index.mjs",
      "file": "vitepress___@vueuse_core.js",
      "fileHash": "9d990347",
      "needsInterop": false
    },
    "vitepress > @vueuse/integrations/useFocusTrap": {
      "src": "../../../../node_modules/@vueuse/integrations/useFocusTrap.mjs",
      "file": "vitepress___@vueuse_integrations_useFocusTrap.js",
      "fileHash": "fe5cb857",
      "needsInterop": false
    },
    "vitepress > mark.js/src/vanilla.js": {
      "src": "../../../../node_modules/mark.js/src/vanilla.js",
      "file": "vitepress___mark__js_src_vanilla__js.js",
      "fileHash": "0c5745d9",
      "needsInterop": false
    },
    "vitepress > minisearch": {
      "src": "../../../../node_modules/minisearch/dist/es/index.js",
      "file": "vitepress___minisearch.js",
      "fileHash": "c68d99cf",
      "needsInterop": false
    },
    "lucide-vue-next": {
      "src": "../../../../node_modules/lucide-vue-next/dist/esm/lucide-vue-next.js",
      "file": "lucide-vue-next.js",
      "fileHash": "0a573347",
      "needsInterop": false
    }
  },
  "chunks": {
    "chunk-GD2PZ323": {
      "file": "chunk-GD2PZ323.js"
    },
    "chunk-LW4I4DCF": {
      "file": "chunk-LW4I4DCF.js"
    },
    "chunk-PZ5AY32C": {
      "file": "chunk-PZ5AY32C.js"
    }
  }
}